src/__init__.py
src/extract.py
src/main.py
mbox_to_json-2.0.0.dist-info/METADATA
mbox_to_json-2.0.0.dist-info/WHEEL
mbox_to_json-2.0.0.dist-info/entry_points.txt
mbox_to_json-2.0.0.dist-info/licenses/LICENSE.txt
mbox_to_json-2.0.0.dist-info/RECORD
