Metadata-Version: 2.4
Name: mbox-to-json
Version: 2.0.0
Summary: MBOX to JSON Converter with attachment extraction and cross-referencing
Project-URL: Homepage, https://github.com/PS1607/mbox-to-json
Project-URL: Repository, https://github.com/PS1607/mbox-to-json.git
Project-URL: Bug Reports, https://github.com/PS1607/mbox-to-json/issues
Project-URL: Source Code, https://github.com/PS1607/mbox-to-json
Author: Adrita Bhattacharya
Author-email: Prakhar Sharma <prakharsharma1607@gmail.com>
Maintainer-email: Prakhar Sharma <prakharsharma1607@gmail.com>
License: MIT
License-File: LICENSE.txt
Keywords: attachment,converter,email,extraction,json,mbox
Classifier: Development Status :: 5 - Production/Stable
Classifier: Intended Audience :: Developers
Classifier: Intended Audience :: End Users/Desktop
Classifier: License :: OSI Approved :: MIT License
Classifier: Operating System :: OS Independent
Classifier: Programming Language :: Python :: 3
Classifier: Programming Language :: Python :: 3.8
Classifier: Programming Language :: Python :: 3.9
Classifier: Programming Language :: Python :: 3.10
Classifier: Programming Language :: Python :: 3.11
Classifier: Programming Language :: Python :: 3.12
Classifier: Topic :: Communications :: Email
Classifier: Topic :: Software Development :: Libraries :: Python Modules
Classifier: Topic :: Utilities
Requires-Python: >=3.8
Requires-Dist: alive-progress>=3.1.0
Requires-Dist: charset-normalizer>=3.0.0
Requires-Dist: pandas>=2.0.0
Provides-Extra: dev
Requires-Dist: black>=22.0.0; extra == 'dev'
Requires-Dist: flake8>=4.0.0; extra == 'dev'
Requires-Dist: mypy>=0.900; extra == 'dev'
Requires-Dist: pytest>=7.0.0; extra == 'dev'
Provides-Extra: test
Requires-Dist: pytest-cov>=3.0.0; extra == 'test'
Requires-Dist: pytest>=7.0.0; extra == 'test'
